mcp_server_waii/__init__.py
mcp_server_waii/__main__.py
mcp_server_waii/server.py
mcp_server_waii-1.0.0.dist-info/licenses/LICENSE
mcp_server_waii-1.0.0.dist-info/METADATA
mcp_server_waii-1.0.0.dist-info/WHEEL
mcp_server_waii-1.0.0.dist-info/entry_points.txt
mcp_server_waii-1.0.0.dist-info/top_level.txt
mcp_server_waii-1.0.0.dist-info/RECORD
