Metadata-Version: 2.4
Name: mcp-server-waii
Version: 1.0.0
Summary: An MCP server implementation for WAII database interactions
Author-email: Swaraj Nayegandhi <swaraj.nayegandhi@waii.ai>
License: Apache-2.0
Project-URL: Documentation, https://github.com/waii-ai/waii-mcp-server#readme
Project-URL: Repository, https://github.com/waii-ai/waii-mcp-server.git
Keywords: mcp,waii,database,ai,nlp,sql
Classifier: Development Status :: 3 - Alpha
Classifier: Intended Audience :: Developers
Classifier: Intended Audience :: Science/Research
Classifier: License :: OSI Approved :: Apache Software License
Classifier: Programming Language :: Python :: 3
Classifier: Programming Language :: Python :: 3.10
Classifier: Programming Language :: Python :: 3.11
Classifier: Topic :: Database
Classifier: Topic :: Scientific/Engineering :: Artificial Intelligence
Classifier: Topic :: Software Development :: Libraries :: Python Modules
Classifier: Operating System :: OS Independent
Requires-Python: >=3.10
License-File: LICENSE
Requires-Dist: mcp>=0.1.0
Requires-Dist: waii-sdk-py>=1.29.2
Requires-Dist: pydantic>=2.0.0
Requires-Dist: pandas>=1.0.0
Dynamic: license-file
